theatre_cli/__init__.py
theatre_cli/config.py
theatre_cli/movie.py
theatre_cli/player.py
theatre_cli-0.1.6.data/scripts/theatre-cli
theatre_cli-0.1.6.dist-info/METADATA
theatre_cli-0.1.6.dist-info/WHEEL
theatre_cli-0.1.6.dist-info/top_level.txt
theatre_cli-0.1.6.dist-info/RECORD
