Metadata-Version: 2.1
Name: theatre-cli
Version: 0.1.6
Summary: A command-line interface to play movies
Home-page: https://github.com/virajsazzala/theatre-cli
Author: SNG Viraj Reddy
Author-email: vir200319@gmail.com
License: MIT
Platform: UNKNOWN
Classifier: Development Status :: 5 - Production/Stable
Classifier: Intended Audience :: End Users/Desktop
Classifier: License :: OSI Approved :: MIT License
Classifier: Programming Language :: Python :: 3
Classifier: Programming Language :: Python :: 3.6
Classifier: Programming Language :: Python :: 3.7
Classifier: Programming Language :: Python :: 3.8
Classifier: Programming Language :: Python :: 3.9
Classifier: Topic :: Utilities
